{
  "project_info": {
    "project_number": "1046032777943",
    "firebase_url": "https://homesky-4b105.firebaseio.com",
    "project_id": "homesky-4b105",
    "storage_bucket": "homesky-4b105.appspot.com"
  },
  "client": [
    {
      "client_info": {
        "mobilesdk_app_id": "1:1046032777943:android:6fa08cbd33e0a4b7",
        "android_client_info": {
          "package_name": "com.homesky.homesky"
        }
      },
      "oauth_client": [
        {
          "client_id": "1046032777943-5s8v8scegppthct1d7jus0nkehb81ut1.apps.googleusercontent.com",
          "client_type": 3
        }
      ],
      "api_key": [
        {
          "current_key": "AIzaSyA1BFgWvZnCkxstaGwrtonT6JXz5l0drFw"
        }
      ],
      "services": {
        "analytics_service": {
          "status": 1
        },
        "appinvite_service": {
          "status": 1,
          "other_platform_oauth_client": []
        },
        "ads_service": {
          "status": 2
        }
      }
    }
  ],
  "configuration_version": "1"
}